docleaf-0.8.3.dist-info/METADATA
docleaf-0.8.3.dist-info/WHEEL
docleaf-0.8.3.dist-info/license_files/LICENSE.md
docleaf-0.8.3.dist-info/license_files/LICENSES_THIRD_PARTY.md
docleaf/copied.py
docleaf/domains.py
docleaf/doxygen.py
docleaf/errors.py
docleaf/__init__.py
docleaf/backend.cp39-win_amd64.pyd
docleaf-0.8.3.dist-info/RECORD
