Metadata-Version: 2.1
Name: docleaf
Version: 0.8.3
Classifier: Development Status :: 3 - Alpha
Classifier: Framework :: Sphinx :: Extension
Classifier: Programming Language :: Python :: 3
Classifier: Topic :: Documentation
Requires-Dist: docutils>=0.12
Requires-Dist: Sphinx>=4.0,!=5.0.0
License-File: LICENSE.md
License-File: LICENSES_THIRD_PARTY.md
Summary: Integrate your doxygen-generated technical documentation into Sphinx
Keywords: sphinx,doxygen
Author-email: Michael Jones <michael.jones@docleaf.io>
Requires-Python: >=3.7
Project-URL: changelog, https://github.com/docleaf-labs/docleaf/blob/main/CHANGELOG.md
Project-URL: repository, https://github.com/docleaf-labs/docleaf
Project-URL: homepage, https://docleaf.io
